Parler/__init__.py
Parler/models.py
Parler/utils.py
Parler/version.py
Parler/with_auth.py
tests/__init__.py
tests/test_feed.py
tests/test_post.py
tests/test_user.py
parler_api-2.7.0.dist-info/METADATA
parler_api-2.7.0.dist-info/WHEEL
parler_api-2.7.0.dist-info/top_level.txt
parler_api-2.7.0.dist-info/RECORD
