Metadata-Version: 2.1
Name: parler-api
Version: 2.7.0
Summary: Parler API library - v2.7
Home-page: https://github.com/konradit/parler-py-api
Author: Konrad Iturbe
Author-email: mail@chernowii.com
License: UNKNOWN
Platform: UNKNOWN
Requires-Python: >=3.6
Requires-Dist: requests
Requires-Dist: python-dotenv
Requires-Dist: termcolor
Requires-Dist: marshmallow
Requires-Dist: pipdate
Requires-Dist: pytest
Requires-Dist: fake-useragent
